plldb/__init__.py
plldb/__main__.py
plldb/cli.py
plldb/debugger.py
plldb/executor.py
plldb/protocol.py
plldb/rest_client.py
plldb/setup.py
plldb/simulator.py
plldb/stack_discovery.py
plldb/websocket_client.py
plldb/cloudformation/__init__.py
plldb/cloudformation/template.yaml
plldb/cloudformation/lambda_functions/__init__.py
plldb/cloudformation/lambda_functions/debugger_instrumentation.py
plldb/cloudformation/lambda_functions/restapi.py
plldb/cloudformation/lambda_functions/websocket_authorize.py
plldb/cloudformation/lambda_functions/websocket_connect.py
plldb/cloudformation/lambda_functions/websocket_default.py
plldb/cloudformation/lambda_functions/websocket_disconnect.py
plldb/cloudformation/layer/__init__.py
plldb/cloudformation/layer/bootstrap
plldb/cloudformation/layer/lambda_runtime.py
plldb/util/__init__.py
plldb/util/cfn.py
plldb-0.1.3.dist-info/METADATA
plldb-0.1.3.dist-info/WHEEL
plldb-0.1.3.dist-info/entry_points.txt
plldb-0.1.3.dist-info/RECORD
