Metadata-Version: 2.4
Name: plldb
Version: 0.1.3
Summary: Python Lambda Local Debugger - Debug AWS Lambda functions locally
Project-URL: Homepage, https://github.com/martin-macak/plldb
Project-URL: Repository, https://github.com/martin-macak/plldb
Project-URL: Bug Tracker, https://github.com/martin-macak/plldb/issues
Project-URL: Documentation, https://github.com/martin-macak/plldb#readme
Author-email: Martin Macak <martin.macak@gmail.com>
Maintainer-email: Martin Macak <martin.macak@gmail.com>
License: MIT
Keywords: aws,debugger,debugging,development,lambda,serverless
Classifier: Development Status :: 4 - Beta
Classifier: Environment :: Console
Classifier: Intended Audience :: Developers
Classifier: License :: OSI Approved :: MIT License
Classifier: Operating System :: OS Independent
Classifier: Programming Language :: Python :: 3
Classifier: Programming Language :: Python :: 3.13
Classifier: Topic :: Software Development :: Debuggers
Classifier: Topic :: Software Development :: Testing
Requires-Python: >=3.13
Requires-Dist: boto3>=1.38.23
Requires-Dist: click>=8.2.1
Requires-Dist: debugpy>=1.8.14
Requires-Dist: pdb-attach>=3.0.1
Requires-Dist: pyyaml>=6.0.2
Requires-Dist: requests>=2.32.0
Requires-Dist: websockets>=14.1
